{
  "annotations": {
    "changelogDate": "20241209160905"
  },
  "applications": "*",
  "dto": "mapstruct",
  "fields": [
    {
      "fieldName": "tenTrangThai",
      "fieldType": "String",
      "fieldValidateRules": ["required", "unique"]
    },
    {
      "fieldName": "moTa",
      "fieldType": "String"
    },
    {
      "fieldName": "createdAt",
      "fieldType": "ZonedDateTime"
    },
    {
      "fieldName": "updatedAt",
      "fieldType": "ZonedDateTime"
    }
  ],
  "name": "TrangThai",
  "pagination": "pagination",
  "relationships": [],
  "searchEngine": "no",
  "service": "serviceClass"
}
